ilff/__init__.py
ilff/__main__.py
ilff/ailff.py
ilff/cat.py
ilff/cilff.py
ilff/cleanindex.py
ilff/compact.py
ilff/getline.py
ilff/getlines.py
ilff/getlinestxt.py
ilff/ilff.py
ilff/ilffgetlines.py
ilff/nlines.py
ilff/reindex.py
ilff/remove.py
ilff/showindex.py
ilff/tee.py
ilff/write.py
tests/TestMWrites.py
tests/__init__.py
tests/test_awrites.py
tests/test_cwrites.py
tests/test_writes.py
ilff-24.12.8.dist-info/LICENSE.txt
ilff-24.12.8.dist-info/METADATA
ilff-24.12.8.dist-info/WHEEL
ilff-24.12.8.dist-info/entry_points.txt
ilff-24.12.8.dist-info/top_level.txt
ilff-24.12.8.dist-info/RECORD
